nyth_dataset/__init__.py
nyth_dataset/nyth.py
nyth_dataset/utils.py
nyth_dataset-0.0.2.dist-info/LICENSE
nyth_dataset-0.0.2.dist-info/METADATA
nyth_dataset-0.0.2.dist-info/WHEEL
nyth_dataset-0.0.2.dist-info/top_level.txt
nyth_dataset-0.0.2.dist-info/RECORD
