Metadata-Version: 2.1
Name: nyth-dataset
Version: 0.0.2
Summary: NYT-H dataset package allows the processing of the NYT-H dataset proposed by Zhu et al., 2020. NYT-H is based on the New York Times 2010 ( NYT2010) dataset proposed by Riedel et al., 2010. The advantage of NYT-H dataset is the manual annotation of the test partition.
Home-page: https://github.com/juanluis17/nyth-dataset
Author: Juan-Luis García-Mendoza
Author-email: Juan-Luis García-Mendoza <jluisgm90@gmail.com>
License: Apache Software License
Project-URL: Homepage, https://github.com/juanluis17/nyth-dataset
Project-URL: Bug Tracker, https://github.com/juanluis17/nyth-dataset/issues
Classifier: Programming Language :: Python :: 3
Classifier: License :: OSI Approved :: Apache Software License
Classifier: Operating System :: OS Independent
Requires-Python: >=3.7
License-File: LICENSE
Requires-Dist: pandas
